cortex_container_tools/__init__.py
cortex_container_tools/server/__init__.py
cortex_container_tools/server/base.py
cortex_container_tools/server/handler.py
cortex_container_tools/server/routes.py
cortex_container_tools/util/__init__.py
cortex_container_tools/util/codecs/__init__.py
cortex_container_tools/util/codecs/_codec.py
cortex_container_tools/util/codecs/json_codec.py
cortex_container_tools/util/codecs/mlflow_codec.py
cortex_container_tools/util/models/__init__.py
cortex_container_tools/util/models/_model.py
cortex_container_tools/util/models/mlflow.py
cortex_container_tools/util/models/trainer.py
cortex_container_tools/util/types/__init__.py
cortex_container_tools/util/types/base.py
cortex_container_tools/util/types/dataplane.py
cortex_container_tools-3.0.4.dist-info/METADATA
cortex_container_tools-3.0.4.dist-info/WHEEL
cortex_container_tools-3.0.4.dist-info/top_level.txt
cortex_container_tools-3.0.4.dist-info/RECORD
