Metadata-Version: 2.1
Name: cortex_container_tools
Version: 3.0.4
Summary: Nearly Human Cortex Container Tools dependency for creating training / deployment containers.
Author: Nearly Human
Author-email: support@nearlyhuman.ai
Keywords: nearlyhuman,nearly human,cortex,container,tools
Requires-Python: >=3.8.10
Requires-Dist: fastapi ~=0.104.0
Requires-Dist: mlflow-skinny ==2.8.0
Requires-Dist: mlserver ==1.2.1
Requires-Dist: cortex-sdk
